{
    "id": 3561165422592,
    "userid": 1234,
    "urgency": 16,
    "priority": 16,
    "t_submit": 1684197127.6564085,
    "t_depend": 1684197127.668735,
    "t_run": 1684197127.685995,
    "t_cleanup": 1684197128.3235948,
    "t_inactive": 1684197128.3259869,
    "state": "INACTIVE",
    "name": "ring_mpifh",
    "ntasks": 448,
    "ncores": 448,
    "duration": 0.0,
    "nnodes": 8,
    "ranks": "[0-7]",
    "nodelist": "flux-sample-[0-7]",
    "success": true,
    "exception_occurred": false,
    "result": "COMPLETED",
    "expiration": 4837797127.0,
    "waitstatus": 0,
    "returncode": 0,
    "runtime": 0.6375997066497803,
    "exception": {
        "occurred": false,
        "severity": "",
        "type": "",
        "note": ""
    }
}