{
    "id": 7082451402752,
    "userid": 1234,
    "urgency": 16,
    "priority": 16,
    "t_submit": 1684195669.7805924,
    "t_depend": 1684195669.7923894,
    "t_run": 1684195669.8080838,
    "t_cleanup": 1684195671.3482194,
    "t_inactive": 1684195671.350525,
    "state": "INACTIVE",
    "name": "ring_mpifh",
    "cwd": "/opt/ompi",
    "ntasks": 280,
    "ncores": 280,
    "duration": 0.0,
    "nnodes": 5,
    "ranks": "[0-4]",
    "nodelist": "flux-sample-[3-7]",
    "success": true,
    "exception_occurred": false,
    "result": "COMPLETED",
    "expiration": 4837795669.0,
    "waitstatus": 0,
    "returncode": 0,
    "runtime": 1.5401356220245361,
    "exception": {
        "occurred": false,
        "severity": "",
        "type": "",
        "note": ""
    }
}