{
    "id": 1654636150784,
    "userid": 1234,
    "urgency": 16,
    "priority": 16,
    "t_submit": 1684195398.0337799,
    "t_depend": 1684195398.0449753,
    "t_run": 1684195398.0586143,
    "t_cleanup": 1684195399.3802812,
    "t_inactive": 1684195399.3819046,
    "state": "INACTIVE",
    "name": "hello_cxx",
    "cwd": "/opt/ompi",
    "ntasks": 168,
    "ncores": 168,
    "duration": 0.0,
    "nnodes": 3,
    "ranks": "[0-2]",
    "nodelist": "flux-sample-[0-2]",
    "success": true,
    "exception_occurred": false,
    "result": "COMPLETED",
    "expiration": 4837795398.0,
    "waitstatus": 0,
    "returncode": 0,
    "runtime": 1.321666955947876,
    "exception": {
        "occurred": false,
        "severity": "",
        "type": "",
        "note": ""
    }
}