{
    "id": 5629192175616,
    "userid": 1234,
    "urgency": 16,
    "priority": 16,
    "t_submit": 1684195583.1602762,
    "t_depend": 1684195583.1720903,
    "t_run": 1684195583.1874347,
    "t_cleanup": 1684195584.7295337,
    "t_inactive": 1684195584.7320225,
    "state": "INACTIVE",
    "name": "ring_usempi",
    "cwd": "/opt/ompi",
    "ntasks": 280,
    "ncores": 280,
    "duration": 0.0,
    "nnodes": 5,
    "ranks": "[0-4]",
    "nodelist": "flux-sample-[3-7]",
    "success": true,
    "exception_occurred": false,
    "result": "COMPLETED",
    "expiration": 4837795583.0,
    "waitstatus": 0,
    "returncode": 0,
    "runtime": 1.5420989990234375,
    "exception": {
        "occurred": false,
        "severity": "",
        "type": "",
        "note": ""
    }
}