{
    "id": 7864722653184,
    "userid": 1234,
    "urgency": 16,
    "priority": 16,
    "t_submit": 1684194681.4148095,
    "t_depend": 1684194681.4269946,
    "t_run": 1684194681.443089,
    "t_cleanup": 1684194683.047088,
    "t_inactive": 1684194683.050468,
    "state": "INACTIVE",
    "name": "ring_mpifh",
    "cwd": "/opt/ompi",
    "ntasks": 336,
    "ncores": 336,
    "duration": 0.0,
    "nnodes": 6,
    "ranks": "[0-5]",
    "nodelist": "flux-sample-[2-7]",
    "success": true,
    "exception_occurred": false,
    "result": "COMPLETED",
    "expiration": 4837794681.0,
    "waitstatus": 0,
    "returncode": 0,
    "runtime": 1.6039988994598389,
    "exception": {
        "occurred": false,
        "severity": "",
        "type": "",
        "note": ""
    }
}